setup.py
salure_helpers/imanage/__init__.py
salure_helpers/imanage/imanage.py
salure_helpers_imanage.egg-info/PKG-INFO
salure_helpers_imanage.egg-info/SOURCES.txt
salure_helpers_imanage.egg-info/dependency_links.txt
salure_helpers_imanage.egg-info/not-zip-safe
salure_helpers_imanage.egg-info/requires.txt
salure_helpers_imanage.egg-info/top_level.txt